protoswift/__init__.py
protoswift/cli.py
protoswift-1.0.0.dist-info/METADATA
protoswift-1.0.0.dist-info/WHEEL
protoswift-1.0.0.dist-info/entry_points.txt
protoswift-1.0.0.dist-info/RECORD
