Metadata-Version: 2.4
Name: protoswift
Version: 1.0.0
Summary: Swiftly scaffold a Python project structure
Author: Linnaeus Bundalian
License: MIT
Requires-Python: >=3.9
Requires-Dist: pyyaml
Requires-Dist: rich
Provides-Extra: test
Requires-Dist: pytest-cov>=4.0.0; extra == 'test'
Requires-Dist: pytest>=7.0.0; extra == 'test'
